{
  "meta": {
    "version": "1.0",
    "lastUpdated": "2025-12-23",
    "totalTopics": 60,
    "publishedCount": 44
  },
  "categories": [
    {
      "id": "degree-guides",
      "name": "Degree Guides",
      "description": "Comprehensive guides for WGU degree programs"
    },
    {
      "id": "course-help",
      "name": "Course Help",
      "description": "Specific course strategies and tips"
    },
    {
      "id": "study-tips",
      "name": "Study Tips",
      "description": "General study strategies for online learners"
    },
    {
      "id": "comparisons",
      "name": "Comparisons",
      "description": "WGU vs other universities"
    },
    {
      "id": "career",
      "name": "Career & Jobs",
      "description": "Career outcomes and job prospects"
    },
    {
      "id": "exam-prep",
      "name": "Exam Preparation",
      "description": "OA and PA preparation strategies"
    }
  ],
  "content": [
    {
      "id": "001",
      "type": "blog",
      "slug": "wgu-mba-complete-guide",
      "title": "WGU MBA Program: Complete Guide to Fast-Track Your Business Degree",
      "primaryKeyword": "WGU MBA",
      "secondaryKeywords": [
        "WGU MBA program",
        "WGU business degree",
        "online MBA WGU",
        "WGU MBA accelerated"
      ],
      "category": "degree-guides",
      "tags": [
        "MBA",
        "Business",
        "Graduate"
      ],
      "priority": 1,
      "status": "published",
      "publishedDate": "2025-12-17",
      "internalLinks": [
        "wgu-oa-exam-tips",
        "wgu-acceleration-guide",
        "wgu-performance-assessment-guide",
        "wgu-vs-snhu-comparison"
      ],
      "estimatedReadTime": 12,
      "notes": "Cover program structure, courses, tips for acceleration, career outcomes"
    },
    {
      "id": "002",
      "type": "blog",
      "slug": "wgu-bsit-guide",
      "title": "WGU BSIT: How to Complete Your IT Degree in Record Time",
      "primaryKeyword": "WGU BSIT",
      "secondaryKeywords": [
        "WGU IT degree",
        "WGU information technology",
        "BSIT WGU",
        "WGU tech degree"
      ],
      "category": "degree-guides",
      "tags": [
        "IT",
        "BSIT",
        "Technology",
        "Undergraduate"
      ],
      "priority": 1,
      "status": "published",
      "publishedDate": "2025-12-17",
      "internalLinks": [
        "wgu-oa-exam-tips",
        "wgu-acceleration-guide",
        "wgu-performance-assessment-guide",
        "wgu-mba-complete-guide"
      ],
      "estimatedReadTime": 10,
      "notes": "Include certification info, course sequence, lab tips"
    },
    {
      "id": "003",
      "type": "blog",
      "slug": "wgu-nursing-program-guide",
      "title": "WGU Nursing Programs: RN to BSN and MSN Pathways Explained",
      "primaryKeyword": "WGU nursing",
      "secondaryKeywords": [
        "WGU RN to BSN",
        "WGU MSN",
        "WGU nursing program",
        "online nursing degree WGU"
      ],
      "category": "degree-guides",
      "tags": [
        "Nursing",
        "Healthcare",
        "BSN",
        "MSN"
      ],
      "priority": 1,
      "status": "published",
      "publishedDate": "2025-12-17",
      "internalLinks": [
        "wgu-clinical-tips",
        "wgu-study-tips"
      ],
      "estimatedReadTime": 11,
      "notes": "Cover clinical requirements, cohort model, state authorization"
    },
    {
      "id": "004",
      "type": "blog",
      "slug": "wgu-vs-snhu-comparison",
      "title": "WGU vs SNHU: Which Online University Is Right for You?",
      "primaryKeyword": "WGU vs SNHU",
      "secondaryKeywords": [
        "WGU or SNHU",
        "SNHU vs WGU",
        "online degree comparison",
        "WGU SNHU which is better"
      ],
      "category": "comparisons",
      "tags": [
        "Comparison",
        "SNHU",
        "Online Education"
      ],
      "priority": 2,
      "status": "published",
      "publishedDate": "2025-12-17",
      "internalLinks": [
        "wgu-oa-exam-tips",
        "wgu-acceleration-guide",
        "wgu-performance-assessment-guide"
      ],
      "estimatedReadTime": 9,
      "notes": "Compare cost, format, accreditation, time to completion, career outcomes"
    },
    {
      "id": "005",
      "type": "blog",
      "slug": "wgu-oa-exam-tips",
      "title": "How to Pass WGU Objective Assessments: Proven OA Study Strategies",
      "primaryKeyword": "WGU OA tips",
      "secondaryKeywords": [
        "WGU objective assessment",
        "pass WGU OA",
        "WGU exam tips",
        "WGU test strategies"
      ],
      "category": "exam-prep",
      "tags": [
        "OA",
        "Exams",
        "Study Tips"
      ],
      "priority": 1,
      "status": "published",
      "publishedDate": "2025-12-16",
      "internalLinks": [
        "wgu-study-tips",
        "wgu-time-management"
      ],
      "estimatedReadTime": 8,
      "notes": "Include pre-assessment strategy, study resources, test day tips"
    },
    {
      "id": "006",
      "type": "blog",
      "slug": "wgu-performance-assessment-guide",
      "title": "WGU Performance Assessments: Write Papers That Pass First Time",
      "primaryKeyword": "WGU PA tips",
      "secondaryKeywords": [
        "WGU performance assessment",
        "WGU papers",
        "WGU writing tips",
        "pass WGU PA"
      ],
      "category": "exam-prep",
      "tags": [
        "PA",
        "Writing",
        "Assessments"
      ],
      "priority": 1,
      "status": "published",
      "publishedDate": "2025-12-17",
      "internalLinks": [
        "wgu-oa-exam-tips",
        "wgu-study-tips"
      ],
      "estimatedReadTime": 10,
      "notes": "Cover rubric reading, task analysis, revision strategies, evaluator expectations"
    },
    {
      "id": "007",
      "type": "blog",
      "slug": "wgu-study-tips-working-adults",
      "title": "WGU Study Tips for Working Adults: Balance Work, Life, and School",
      "primaryKeyword": "WGU study tips",
      "secondaryKeywords": [
        "WGU time management",
        "study while working",
        "WGU balance",
        "adult learner tips WGU"
      ],
      "category": "study-tips",
      "tags": [
        "Study Tips",
        "Time Management",
        "Work-Life Balance"
      ],
      "priority": 2,
      "status": "published",
      "publishedDate": "2025-12-17",
      "internalLinks": [
        "wgu-oa-exam-tips",
        "wgu-acceleration-guide"
      ],
      "estimatedReadTime": 7,
      "notes": "Practical tips for busy professionals, scheduling strategies"
    },
    {
      "id": "008",
      "type": "blog",
      "slug": "wgu-acceleration-guide",
      "title": "How to Accelerate Through WGU: Complete Your Degree Faster",
      "primaryKeyword": "WGU acceleration",
      "secondaryKeywords": [
        "accelerate WGU degree",
        "WGU fast track",
        "finish WGU quickly",
        "WGU speed"
      ],
      "category": "study-tips",
      "tags": [
        "Acceleration",
        "Fast Track",
        "Strategy"
      ],
      "priority": 1,
      "status": "published",
      "publishedDate": "2025-12-16",
      "internalLinks": [
        "wgu-study-tips-working-adults",
        "wgu-oa-exam-tips"
      ],
      "estimatedReadTime": 11,
      "notes": "Cover CU loading, course sequencing, mentor communication, transfer credits"
    },
    {
      "id": "009",
      "type": "blog",
      "slug": "wgu-c779-web-development",
      "title": "WGU C779 Web Development Foundations: Complete Study Guide",
      "primaryKeyword": "WGU C779",
      "secondaryKeywords": [
        "C779 study guide",
        "WGU web development",
        "C779 OA",
        "C779 tips"
      ],
      "category": "course-help",
      "tags": [
        "C779",
        "Web Development",
        "IT Courses"
      ],
      "priority": 2,
      "status": "published",
      "publishedDate": "2025-12-18",
      "internalLinks": [
        "wgu-bsit-guide",
        "wgu-oa-exam-tips"
      ],
      "estimatedReadTime": 8,
      "notes": "HTML, CSS, JavaScript fundamentals, certification prep"
    },
    {
      "id": "010",
      "type": "blog",
      "slug": "wgu-d080-global-business",
      "title": "WGU D080 Global Business: How to Pass This Challenging Course",
      "primaryKeyword": "WGU D080",
      "secondaryKeywords": [
        "D080 study guide",
        "WGU global business",
        "D080 tips",
        "D080 OA"
      ],
      "category": "course-help",
      "tags": [
        "D080",
        "Business",
        "MBA Courses"
      ],
      "priority": 2,
      "status": "published",
      "publishedDate": "2025-12-18",
      "internalLinks": [
        "wgu-mba-complete-guide",
        "wgu-oa-exam-tips"
      ],
      "estimatedReadTime": 7,
      "notes": "Focus on international business concepts, cultural dimensions"
    },
    {
      "id": "011",
      "type": "blog",
      "slug": "wgu-capstone-guide",
      "title": "WGU Capstone Project: Step-by-Step Guide to Completing Your Final Project",
      "primaryKeyword": "WGU capstone",
      "secondaryKeywords": [
        "WGU capstone project",
        "WGU final project",
        "capstone tips WGU",
        "WGU capstone help"
      ],
      "category": "exam-prep",
      "tags": [
        "Capstone",
        "Final Project",
        "Graduation"
      ],
      "priority": 1,
      "status": "published",
      "publishedDate": "2025-12-17",
      "internalLinks": [
        "wgu-performance-assessment-guide",
        "wgu-mba-complete-guide"
      ],
      "estimatedReadTime": 12,
      "notes": "Topic selection, research methods, writing structure, committee expectations"
    },
    {
      "id": "012",
      "type": "blog",
      "slug": "wgu-jobs-after-graduation",
      "title": "Jobs After WGU: Career Opportunities and Salary Expectations",
      "primaryKeyword": "WGU jobs",
      "secondaryKeywords": [
        "WGU career outcomes",
        "WGU salary",
        "jobs after WGU degree",
        "WGU employment"
      ],
      "category": "career",
      "tags": [
        "Career",
        "Jobs",
        "Salary",
        "Employment"
      ],
      "priority": 2,
      "status": "published",
      "publishedDate": "2025-12-17",
      "internalLinks": [
        "wgu-mba-complete-guide",
        "wgu-bsit-guide"
      ],
      "estimatedReadTime": 9,
      "notes": "Include salary data, employer reception, interview tips"
    },
    {
      "id": "013",
      "type": "blog",
      "slug": "wgu-transfer-credits-guide",
      "title": "WGU Transfer Credits: How to Maximize Credits and Save Time",
      "primaryKeyword": "WGU transfer credits",
      "secondaryKeywords": [
        "transfer credits to WGU",
        "WGU credit transfer",
        "WGU prior learning",
        "WGU transcripts"
      ],
      "category": "study-tips",
      "tags": [
        "Transfer Credits",
        "Enrollment",
        "Getting Started"
      ],
      "priority": 2,
      "status": "published",
      "publishedDate": "2025-12-17",
      "internalLinks": [
        "wgu-acceleration-guide",
        "wgu-certification-guide"
      ],
      "estimatedReadTime": 8,
      "notes": "Cover Sophia, Study.com, Straighterline, certifications"
    },
    {
      "id": "014",
      "type": "blog",
      "slug": "wgu-certification-guide",
      "title": "WGU IT Certifications: Which Certs Are Included and How to Pass Them",
      "primaryKeyword": "WGU certifications",
      "secondaryKeywords": [
        "WGU IT certs",
        "WGU CompTIA",
        "WGU AWS",
        "certifications included WGU"
      ],
      "category": "degree-guides",
      "tags": [
        "Certifications",
        "IT",
        "CompTIA",
        "AWS"
      ],
      "priority": 1,
      "status": "published",
      "publishedDate": "2025-12-17",
      "internalLinks": [
        "wgu-bsit-guide",
        "wgu-oa-exam-tips"
      ],
      "estimatedReadTime": 10,
      "notes": "List all certs by program, study strategies, voucher info"
    },
    {
      "id": "015",
      "type": "blog",
      "slug": "wgu-vs-traditional-college",
      "title": "WGU vs Traditional College: Is an Online Competency-Based Degree Worth It?",
      "primaryKeyword": "WGU vs traditional college",
      "secondaryKeywords": [
        "online vs traditional degree",
        "competency based education",
        "WGU worth it",
        "WGU legitimacy"
      ],
      "category": "comparisons",
      "tags": [
        "Comparison",
        "Online Education",
        "Traditional"
      ],
      "priority": 2,
      "status": "published",
      "publishedDate": "2025-12-18",
      "internalLinks": [
        "wgu-jobs-after-graduation",
        "wgu-acceleration-guide"
      ],
      "estimatedReadTime": 11,
      "notes": "Address employer perceptions, accreditation, flexibility, outcomes"
    },
    {
      "id": "016",
      "type": "landing",
      "slug": "wgu-mba-help",
      "title": "WGU MBA Help: Expert Assistance for Your Business Degree",
      "primaryKeyword": "WGU MBA help",
      "secondaryKeywords": [
        "WGU MBA tutoring",
        "MBA coursework help",
        "WGU MBA assistance",
        "MBA degree support"
      ],
      "category": "degree-guides",
      "tags": [
        "MBA",
        "Services",
        "Help"
      ],
      "priority": 1,
      "status": "pending",
      "internalLinks": [
        "wgu-mba-complete-guide",
        "wgu-capstone-guide"
      ],
      "estimatedReadTime": 5,
      "notes": "Service-focused landing page for MBA students"
    },
    {
      "id": "017",
      "type": "landing",
      "slug": "wgu-it-help",
      "title": "WGU IT Degree Help: Pass Your Tech Courses and Certifications",
      "primaryKeyword": "WGU IT help",
      "secondaryKeywords": [
        "WGU BSIT help",
        "WGU IT tutoring",
        "WGU tech degree help",
        "IT coursework assistance"
      ],
      "category": "degree-guides",
      "tags": [
        "IT",
        "Services",
        "Help"
      ],
      "priority": 1,
      "status": "pending",
      "internalLinks": [
        "wgu-bsit-guide",
        "wgu-certification-guide"
      ],
      "estimatedReadTime": 5,
      "notes": "Service-focused landing page for IT students"
    },
    {
      "id": "018",
      "type": "landing",
      "slug": "wgu-nursing-help",
      "title": "WGU Nursing Help: Expert Support for RN to BSN and MSN Students",
      "primaryKeyword": "WGU nursing help",
      "secondaryKeywords": [
        "WGU RN to BSN help",
        "nursing coursework help",
        "WGU MSN help",
        "nursing degree assistance"
      ],
      "category": "degree-guides",
      "tags": [
        "Nursing",
        "Services",
        "Help"
      ],
      "priority": 1,
      "status": "pending",
      "internalLinks": [
        "wgu-nursing-program-guide"
      ],
      "estimatedReadTime": 5,
      "notes": "Service-focused landing page for nursing students"
    },
    {
      "id": "019",
      "type": "blog",
      "slug": "wgu-accounting-degree-guide",
      "title": "WGU Accounting Degree: Your Path to CPA and Beyond",
      "primaryKeyword": "WGU accounting",
      "secondaryKeywords": [
        "WGU accounting degree",
        "WGU BSBA accounting",
        "online accounting degree",
        "WGU CPA"
      ],
      "category": "degree-guides",
      "tags": [
        "Accounting",
        "Business",
        "CPA"
      ],
      "priority": 2,
      "status": "published",
      "publishedDate": "2025-12-19",
      "internalLinks": [
        "wgu-mba-complete-guide",
        "wgu-jobs-after-graduation"
      ],
      "estimatedReadTime": 9,
      "notes": "Cover CPA eligibility, course sequence, career paths"
    },
    {
      "id": "020",
      "type": "blog",
      "slug": "wgu-cybersecurity-degree-guide",
      "title": "WGU Cybersecurity Degree: Launch Your InfoSec Career",
      "primaryKeyword": "WGU cybersecurity",
      "secondaryKeywords": [
        "WGU cybersecurity degree",
        "WGU infosec",
        "online cybersecurity degree",
        "WGU security+"
      ],
      "category": "degree-guides",
      "tags": [
        "Cybersecurity",
        "IT",
        "InfoSec"
      ],
      "priority": 1,
      "status": "published",
      "publishedDate": "2025-12-18",
      "internalLinks": [
        "wgu-bsit-guide",
        "wgu-certification-guide"
      ],
      "estimatedReadTime": 10,
      "notes": "Cover certs included, lab requirements, career outlook"
    },
    {
      "id": "021",
      "type": "blog",
      "slug": "wgu-data-analytics-guide",
      "title": "WGU Data Analytics Degree: Skills and Career Opportunities",
      "primaryKeyword": "WGU data analytics",
      "secondaryKeywords": [
        "WGU data science",
        "WGU analytics degree",
        "online data analytics",
        "WGU MSDA"
      ],
      "category": "degree-guides",
      "tags": [
        "Data Analytics",
        "IT",
        "Data Science"
      ],
      "priority": 2,
      "status": "published",
      "publishedDate": "2025-12-19",
      "internalLinks": [
        "wgu-bsit-guide",
        "wgu-jobs-after-graduation"
      ],
      "estimatedReadTime": 9,
      "notes": "Cover tools taught, projects, career paths"
    },
    {
      "id": "022",
      "type": "blog",
      "slug": "wgu-teaching-degree-guide",
      "title": "WGU Teaching Degrees: Become a Licensed Teacher Online",
      "primaryKeyword": "WGU teaching degree",
      "secondaryKeywords": [
        "WGU education degree",
        "WGU teacher certification",
        "online teaching degree",
        "WGU MAT"
      ],
      "category": "degree-guides",
      "tags": [
        "Education",
        "Teaching",
        "Licensure"
      ],
      "priority": 2,
      "status": "published",
      "publishedDate": "2025-12-21",
      "internalLinks": [
        "wgu-capstone-guide",
        "wgu-study-tips-working-adults"
      ],
      "estimatedReadTime": 10,
      "notes": "Cover state licensure, student teaching, demonstration teaching"
    },
    {
      "id": "023",
      "type": "blog",
      "slug": "wgu-c170-data-management",
      "title": "WGU C170 Data Management: SQL and Database Fundamentals Guide",
      "primaryKeyword": "WGU C170",
      "secondaryKeywords": [
        "C170 study guide",
        "WGU SQL course",
        "C170 OA tips",
        "WGU database course"
      ],
      "category": "course-help",
      "tags": [
        "C170",
        "SQL",
        "Databases",
        "IT Courses"
      ],
      "priority": 3,
      "status": "published",
      "publishedDate": "2025-12-21",
      "internalLinks": [
        "wgu-bsit-guide",
        "wgu-oa-exam-tips"
      ],
      "estimatedReadTime": 8,
      "notes": "SQL syntax, ER diagrams, normalization concepts"
    },
    {
      "id": "024",
      "type": "blog",
      "slug": "wgu-c724-information-systems-management",
      "title": "WGU C724: Information Systems Management Study Guide",
      "primaryKeyword": "WGU C724",
      "secondaryKeywords": [
        "C724 study guide",
        "WGU information systems",
        "C724 OA",
        "C724 tips"
      ],
      "category": "course-help",
      "tags": [
        "C724",
        "IS Management",
        "MBA Courses"
      ],
      "priority": 3,
      "status": "published",
      "publishedDate": "2025-12-21",
      "internalLinks": [
        "wgu-mba-complete-guide",
        "wgu-oa-exam-tips"
      ],
      "estimatedReadTime": 7,
      "notes": "Cover IT governance, strategy alignment, project management"
    },
    {
      "id": "025",
      "type": "blog",
      "slug": "wgu-c768-technical-communication",
      "title": "WGU C768 Technical Communication: PA Tips and Writing Guide",
      "primaryKeyword": "WGU C768",
      "secondaryKeywords": [
        "C768 tips",
        "WGU technical writing",
        "C768 PA guide",
        "C768 help"
      ],
      "category": "course-help",
      "tags": [
        "C768",
        "Writing",
        "Technical Communication"
      ],
      "priority": 3,
      "status": "pending",
      "internalLinks": [
        "wgu-performance-assessment-guide",
        "wgu-bsit-guide"
      ],
      "estimatedReadTime": 8,
      "notes": "Document structure, audience analysis, visuals and formatting"
    },
    {
      "id": "026",
      "type": "blog",
      "slug": "wgu-vs-gcu-comparison",
      "title": "WGU vs GCU: Comparing Two Popular Online Universities",
      "primaryKeyword": "WGU vs GCU",
      "secondaryKeywords": [
        "Grand Canyon University vs WGU",
        "GCU or WGU",
        "WGU GCU comparison",
        "online degree comparison"
      ],
      "category": "comparisons",
      "tags": [
        "Comparison",
        "GCU",
        "Online Education"
      ],
      "priority": 3,
      "status": "published",
      "publishedDate": "2025-12-19",
      "internalLinks": [
        "wgu-vs-snhu-comparison",
        "wgu-vs-traditional-college"
      ],
      "estimatedReadTime": 9,
      "notes": "Compare cost, format, religious affiliation, outcomes"
    },
    {
      "id": "027",
      "type": "blog",
      "slug": "wgu-vs-purdue-global",
      "title": "WGU vs Purdue Global: Which Online University Is Better?",
      "primaryKeyword": "WGU vs Purdue Global",
      "secondaryKeywords": [
        "Purdue Global vs WGU",
        "WGU Purdue comparison",
        "online university comparison"
      ],
      "category": "comparisons",
      "tags": [
        "Comparison",
        "Purdue Global",
        "Online Education"
      ],
      "priority": 3,
      "status": "published",
      "publishedDate": "2025-12-19",
      "internalLinks": [
        "wgu-vs-snhu-comparison",
        "wgu-vs-gcu-comparison"
      ],
      "estimatedReadTime": 9,
      "notes": "Compare format, pacing, accreditation, cost"
    },
    {
      "id": "028",
      "type": "blog",
      "slug": "wgu-mentor-tips",
      "title": "How to Work With Your WGU Mentor: Tips for Success",
      "primaryKeyword": "WGU mentor",
      "secondaryKeywords": [
        "WGU program mentor",
        "mentor relationship WGU",
        "WGU mentor tips",
        "WGU mentor calls"
      ],
      "category": "study-tips",
      "tags": [
        "Mentor",
        "Success Tips",
        "Communication"
      ],
      "priority": 2,
      "status": "published",
      "publishedDate": "2025-01-15",
      "internalLinks": [
        "wgu-acceleration-guide",
        "wgu-study-tips-working-adults"
      ],
      "estimatedReadTime": 6,
      "notes": "Communication strategies, setting expectations, asking for help"
    },
    {
      "id": "029",
      "type": "blog",
      "slug": "wgu-proctored-exam-guide",
      "title": "WGU Proctored Exams: What to Expect and How to Prepare",
      "primaryKeyword": "WGU proctored exam",
      "secondaryKeywords": [
        "WGU exam proctoring",
        "WGU OA proctored",
        "ExamSoft WGU",
        "proctoring tips WGU"
      ],
      "category": "exam-prep",
      "tags": [
        "Proctoring",
        "OA",
        "Exams"
      ],
      "priority": 2,
      "status": "published",
      "publishedDate": "2025-12-17",
      "internalLinks": [
        "wgu-oa-exam-tips",
        "wgu-study-tips-working-adults"
      ],
      "estimatedReadTime": 7,
      "notes": "Technical requirements, environment setup, exam day process"
    },
    {
      "id": "030",
      "type": "blog",
      "slug": "sophia-learning-wgu-transfer",
      "title": "Sophia Learning for WGU: Which Courses Transfer and How to Use It",
      "primaryKeyword": "Sophia Learning WGU",
      "secondaryKeywords": [
        "Sophia courses WGU",
        "Sophia transfer credits",
        "WGU Sophia",
        "Sophia for WGU students"
      ],
      "category": "study-tips",
      "tags": [
        "Sophia",
        "Transfer Credits",
        "Cost Savings"
      ],
      "priority": 2,
      "status": "published",
      "internalLinks": [
        "wgu-transfer-credits-guide",
        "wgu-acceleration-guide"
      ],
      "estimatedReadTime": 8,
      "notes": "Course mapping, strategies, timing before enrollment",
      "publishedDate": "2025-12-18"
    },
    {
      "id": "031",
      "type": "blog",
      "slug": "study-com-wgu-transfer",
      "title": "Study.com for WGU: Maximize Transfer Credits and Save Money",
      "primaryKeyword": "Study.com WGU",
      "secondaryKeywords": [
        "Study.com transfer credits",
        "WGU Study.com courses",
        "Study.com for WGU"
      ],
      "category": "study-tips",
      "tags": [
        "Study.com",
        "Transfer Credits",
        "Cost Savings"
      ],
      "priority": 2,
      "status": "published",
      "internalLinks": [
        "wgu-transfer-credits-guide",
        "sophia-learning-wgu-transfer"
      ],
      "estimatedReadTime": 8,
      "notes": "Course mapping, subscription tips, proctored exams",
      "publishedDate": "2025-12-18"
    },
    {
      "id": "032",
      "type": "blog",
      "slug": "wgu-financial-aid-guide",
      "title": "WGU Financial Aid: Scholarships, Grants, and Payment Options",
      "primaryKeyword": "WGU financial aid",
      "secondaryKeywords": [
        "WGU scholarships",
        "WGU grants",
        "WGU tuition",
        "pay for WGU"
      ],
      "category": "study-tips",
      "tags": [
        "Financial Aid",
        "Scholarships",
        "Tuition"
      ],
      "priority": 2,
      "status": "published",
      "publishedDate": "2025-01-15",
      "internalLinks": [
        "wgu-transfer-credits-guide",
        "wgu-acceleration-guide"
      ],
      "estimatedReadTime": 9,
      "notes": "FAFSA, WGU scholarships, employer tuition reimbursement"
    },
    {
      "id": "033",
      "type": "landing",
      "slug": "wgu-capstone-help",
      "title": "WGU Capstone Help: Expert Assistance for Your Final Project",
      "primaryKeyword": "WGU capstone help",
      "secondaryKeywords": [
        "WGU capstone assistance",
        "capstone project help",
        "WGU final project help"
      ],
      "category": "exam-prep",
      "tags": [
        "Capstone",
        "Services",
        "Help"
      ],
      "priority": 1,
      "status": "pending",
      "internalLinks": [
        "wgu-capstone-guide",
        "wgu-performance-assessment-guide"
      ],
      "estimatedReadTime": 5,
      "notes": "Service-focused landing page for capstone students"
    },
    {
      "id": "034",
      "type": "landing",
      "slug": "wgu-exam-help",
      "title": "WGU Exam Help: Pass Your OAs With Expert Support",
      "primaryKeyword": "WGU exam help",
      "secondaryKeywords": [
        "WGU OA help",
        "WGU test help",
        "WGU assessment help",
        "pass WGU exams"
      ],
      "category": "exam-prep",
      "tags": [
        "Exams",
        "OA",
        "Services",
        "Help"
      ],
      "priority": 1,
      "status": "pending",
      "internalLinks": [
        "wgu-oa-exam-tips",
        "wgu-proctored-exam-guide"
      ],
      "estimatedReadTime": 5,
      "notes": "Service-focused landing page for OA assistance"
    },
    {
      "id": "035",
      "type": "blog",
      "slug": "wgu-healthcare-management-guide",
      "title": "WGU Healthcare Management Degree: Career Paths and Program Guide",
      "primaryKeyword": "WGU healthcare management",
      "secondaryKeywords": [
        "WGU health administration",
        "WGU MHA",
        "healthcare management degree online"
      ],
      "category": "degree-guides",
      "tags": [
        "Healthcare",
        "Management",
        "MHA"
      ],
      "priority": 2,
      "status": "published",
      "internalLinks": [
        "wgu-nursing-program-guide",
        "wgu-mba-complete-guide"
      ],
      "estimatedReadTime": 9,
      "notes": "Cover career paths, program structure, industry outlook",
      "publishedDate": "2025-12-22"
    },
    {
      "id": "036",
      "type": "blog",
      "slug": "wgu-human-resources-guide",
      "title": "WGU Human Resources Degree: Your Path to HR Leadership",
      "primaryKeyword": "WGU human resources",
      "secondaryKeywords": [
        "WGU HR degree",
        "WGU SHRM",
        "human resources degree online",
        "WGU HR management"
      ],
      "category": "degree-guides",
      "tags": [
        "HR",
        "Human Resources",
        "Business"
      ],
      "priority": 2,
      "status": "published",
      "internalLinks": [
        "wgu-mba-complete-guide",
        "wgu-jobs-after-graduation"
      ],
      "estimatedReadTime": 9,
      "notes": "Cover SHRM certification, career paths, course highlights",
      "publishedDate": "2025-12-22"
    },
    {
      "id": "037",
      "type": "blog",
      "slug": "wgu-project-management-guide",
      "title": "WGU Project Management: Degree, Certifications, and Career Guide",
      "primaryKeyword": "WGU project management",
      "secondaryKeywords": [
        "WGU PMP",
        "WGU MSPM",
        "project management degree online",
        "WGU PM certification"
      ],
      "category": "degree-guides",
      "tags": [
        "Project Management",
        "PMP",
        "Business"
      ],
      "priority": 2,
      "status": "published",
      "internalLinks": [
        "wgu-mba-complete-guide",
        "wgu-certification-guide"
      ],
      "estimatedReadTime": 9,
      "notes": "Cover PMP prep, MSPM program, career outlook",
      "publishedDate": "2025-12-23"
    },
    {
      "id": "038",
      "type": "blog",
      "slug": "wgu-cloud-computing-guide",
      "title": "WGU Cloud Computing Degree: AWS, Azure, and Career Opportunities",
      "primaryKeyword": "WGU cloud computing",
      "secondaryKeywords": [
        "WGU AWS certification",
        "WGU cloud degree",
        "cloud computing degree online"
      ],
      "category": "degree-guides",
      "tags": [
        "Cloud Computing",
        "AWS",
        "Azure",
        "IT"
      ],
      "priority": 2,
      "status": "published",
      "internalLinks": [
        "wgu-bsit-guide",
        "wgu-certification-guide"
      ],
      "estimatedReadTime": 10,
      "notes": "Cover cloud certs included, hands-on labs, career outlook",
      "publishedDate": "2025-12-23"
    },
    {
      "id": "039",
      "type": "blog",
      "slug": "wgu-software-engineering-guide",
      "title": "WGU Software Engineering Degree: Become a Developer",
      "primaryKeyword": "WGU software engineering",
      "secondaryKeywords": [
        "WGU software development",
        "WGU computer science",
        "software engineering degree online"
      ],
      "category": "degree-guides",
      "tags": [
        "Software Engineering",
        "Programming",
        "IT"
      ],
      "priority": 2,
      "status": "published",
      "internalLinks": [
        "wgu-bsit-guide",
        "wgu-jobs-after-graduation"
      ],
      "estimatedReadTime": 10,
      "notes": "Cover languages taught, capstone project, job outcomes",
      "publishedDate": "2025-12-22"
    },
    {
      "id": "040",
      "type": "blog",
      "slug": "wgu-network-operations-guide",
      "title": "WGU Network Operations Degree: CCNA and Network Engineering Path",
      "primaryKeyword": "WGU network operations",
      "secondaryKeywords": [
        "WGU CCNA",
        "WGU networking degree",
        "network engineering degree online"
      ],
      "category": "degree-guides",
      "tags": [
        "Networking",
        "CCNA",
        "IT"
      ],
      "priority": 3,
      "status": "published",
      "internalLinks": [
        "wgu-bsit-guide",
        "wgu-certification-guide"
      ],
      "estimatedReadTime": 9,
      "notes": "Cover Cisco certs, network labs, career paths",
      "publishedDate": "2025-12-23"
    },
    {
      "id": "041",
      "type": "blog",
      "slug": "wgu-marketing-degree-guide",
      "title": "WGU Marketing Degree: Digital Marketing Skills and Career Paths",
      "primaryKeyword": "WGU marketing degree",
      "secondaryKeywords": [
        "WGU digital marketing",
        "WGU BSBM marketing",
        "online marketing degree"
      ],
      "category": "degree-guides",
      "tags": [
        "Marketing",
        "Business",
        "Digital Marketing"
      ],
      "priority": 3,
      "status": "published",
      "internalLinks": [
        "wgu-mba-complete-guide",
        "wgu-jobs-after-graduation"
      ],
      "estimatedReadTime": 8,
      "notes": "Cover digital marketing skills, career outcomes",
      "publishedDate": "2025-12-23"
    },
    {
      "id": "042",
      "type": "blog",
      "slug": "wgu-supply-chain-management",
      "title": "WGU Supply Chain Management: Degree and Career Opportunities",
      "primaryKeyword": "WGU supply chain",
      "secondaryKeywords": [
        "WGU operations management",
        "supply chain degree online",
        "WGU logistics"
      ],
      "category": "degree-guides",
      "tags": [
        "Supply Chain",
        "Operations",
        "Business"
      ],
      "priority": 3,
      "status": "published",
      "internalLinks": [
        "wgu-mba-complete-guide",
        "wgu-jobs-after-graduation"
      ],
      "estimatedReadTime": 8,
      "notes": "Cover industry demand, skills taught, career paths",
      "publishedDate": "2025-12-23"
    },
    {
      "id": "043",
      "type": "blog",
      "slug": "wgu-c484-organizational-behavior",
      "title": "WGU C484 Organizational Behavior: Study Guide and OA Tips",
      "primaryKeyword": "WGU C484",
      "secondaryKeywords": [
        "C484 study guide",
        "WGU organizational behavior",
        "C484 OA tips"
      ],
      "category": "course-help",
      "tags": [
        "C484",
        "OB",
        "Business Courses"
      ],
      "priority": 3,
      "status": "pending",
      "internalLinks": [
        "wgu-mba-complete-guide",
        "wgu-oa-exam-tips"
      ],
      "estimatedReadTime": 7,
      "notes": "Cover motivation theories, leadership styles, team dynamics"
    },
    {
      "id": "044",
      "type": "blog",
      "slug": "wgu-c483-principles-management",
      "title": "WGU C483 Principles of Management: Complete Study Guide",
      "primaryKeyword": "WGU C483",
      "secondaryKeywords": [
        "C483 study guide",
        "WGU management course",
        "C483 OA tips"
      ],
      "category": "course-help",
      "tags": [
        "C483",
        "Management",
        "Business Courses"
      ],
      "priority": 3,
      "status": "pending",
      "internalLinks": [
        "wgu-mba-complete-guide",
        "wgu-oa-exam-tips"
      ],
      "estimatedReadTime": 7,
      "notes": "Cover planning, organizing, leading, controlling"
    },
    {
      "id": "045",
      "type": "blog",
      "slug": "wgu-c214-financial-management",
      "title": "WGU C214 Financial Management: OA Prep and Study Tips",
      "primaryKeyword": "WGU C214",
      "secondaryKeywords": [
        "C214 study guide",
        "WGU finance course",
        "C214 OA tips"
      ],
      "category": "course-help",
      "tags": [
        "C214",
        "Finance",
        "MBA Courses"
      ],
      "priority": 3,
      "status": "pending",
      "internalLinks": [
        "wgu-mba-complete-guide",
        "wgu-oa-exam-tips"
      ],
      "estimatedReadTime": 8,
      "notes": "Cover TVM, ratio analysis, capital budgeting"
    },
    {
      "id": "046",
      "type": "blog",
      "slug": "wgu-c715-organizational-leadership",
      "title": "WGU C715 Organizational Leadership: Graduate Course Guide",
      "primaryKeyword": "WGU C715",
      "secondaryKeywords": [
        "C715 study guide",
        "WGU leadership course",
        "C715 tips"
      ],
      "category": "course-help",
      "tags": [
        "C715",
        "Leadership",
        "MBA Courses"
      ],
      "priority": 3,
      "status": "pending",
      "internalLinks": [
        "wgu-mba-complete-guide",
        "wgu-oa-exam-tips"
      ],
      "estimatedReadTime": 7,
      "notes": "Cover leadership theories, change management, ethics"
    },
    {
      "id": "047",
      "type": "blog",
      "slug": "wgu-c493-scripting-programming",
      "title": "WGU C493 Scripting and Programming: Python Course Guide",
      "primaryKeyword": "WGU C493",
      "secondaryKeywords": [
        "C493 study guide",
        "WGU Python course",
        "C493 tips",
        "WGU scripting"
      ],
      "category": "course-help",
      "tags": [
        "C493",
        "Python",
        "Programming",
        "IT Courses"
      ],
      "priority": 3,
      "status": "pending",
      "internalLinks": [
        "wgu-bsit-guide",
        "wgu-software-engineering-guide"
      ],
      "estimatedReadTime": 8,
      "notes": "Cover Python basics, data structures, algorithms"
    },
    {
      "id": "048",
      "type": "blog",
      "slug": "wgu-d191-advanced-data-management",
      "title": "WGU D191 Advanced Data Management: PostgreSQL Guide",
      "primaryKeyword": "WGU D191",
      "secondaryKeywords": [
        "D191 study guide",
        "WGU PostgreSQL",
        "D191 PA tips",
        "advanced SQL WGU"
      ],
      "category": "course-help",
      "tags": [
        "D191",
        "PostgreSQL",
        "SQL",
        "IT Courses"
      ],
      "priority": 3,
      "status": "pending",
      "internalLinks": [
        "wgu-c170-data-management",
        "wgu-bsit-guide"
      ],
      "estimatedReadTime": 9,
      "notes": "Cover stored procedures, triggers, ETL concepts"
    },
    {
      "id": "049",
      "type": "blog",
      "slug": "wgu-c846-business-of-it",
      "title": "WGU C846 Business of IT: Project+ Certification Guide",
      "primaryKeyword": "WGU C846",
      "secondaryKeywords": [
        "C846 study guide",
        "WGU Project+",
        "CompTIA Project+ WGU"
      ],
      "category": "course-help",
      "tags": [
        "C846",
        "Project+",
        "Certifications",
        "IT Courses"
      ],
      "priority": 3,
      "status": "pending",
      "internalLinks": [
        "wgu-certification-guide",
        "wgu-bsit-guide"
      ],
      "estimatedReadTime": 8,
      "notes": "Cover Project+ objectives, study strategies, exam day"
    },
    {
      "id": "050",
      "type": "blog",
      "slug": "wgu-d278-scripting-programming",
      "title": "WGU D278 Scripting and Programming Applications: Java Guide",
      "primaryKeyword": "WGU D278",
      "secondaryKeywords": [
        "D278 study guide",
        "WGU Java course",
        "D278 PA tips"
      ],
      "category": "course-help",
      "tags": [
        "D278",
        "Java",
        "Programming",
        "IT Courses"
      ],
      "priority": 3,
      "status": "pending",
      "internalLinks": [
        "wgu-software-engineering-guide",
        "wgu-bsit-guide"
      ],
      "estimatedReadTime": 9,
      "notes": "Cover OOP concepts, Java syntax, project requirements"
    },
    {
      "id": "051",
      "type": "blog",
      "slug": "wgu-one-term-graduation-guide",
      "title": "How to Graduate WGU in One Term: The Ultimate Acceleration Guide",
      "primaryKeyword": "WGU one term",
      "secondaryKeywords": [
        "graduate WGU in one term",
        "WGU single term graduation",
        "WGU fastest graduation"
      ],
      "category": "study-tips",
      "tags": [
        "Acceleration",
        "One Term",
        "Fast Track"
      ],
      "priority": 1,
      "status": "published",
      "publishedDate": "2025-12-18",
      "internalLinks": [
        "wgu-acceleration-guide",
        "wgu-transfer-credits-guide"
      ],
      "estimatedReadTime": 12,
      "notes": "Real strategies, time commitments, course selection"
    },
    {
      "id": "052",
      "type": "blog",
      "slug": "wgu-student-success-stories",
      "title": "WGU Success Stories: How Real Students Completed Their Degrees",
      "primaryKeyword": "WGU success stories",
      "secondaryKeywords": [
        "WGU graduate stories",
        "WGU reviews",
        "WGU testimonials",
        "WGU worth it"
      ],
      "category": "career",
      "tags": [
        "Success Stories",
        "Testimonials",
        "Motivation"
      ],
      "priority": 2,
      "status": "published",
      "internalLinks": [
        "wgu-jobs-after-graduation",
        "wgu-acceleration-guide"
      ],
      "estimatedReadTime": 8,
      "notes": "Compile anonymized success patterns, timelines, tips",
      "publishedDate": "2025-12-23"
    },
    {
      "id": "053",
      "type": "blog",
      "slug": "wgu-employer-perception",
      "title": "Do Employers Respect WGU Degrees? What Hiring Managers Really Think",
      "primaryKeyword": "WGU employer perception",
      "secondaryKeywords": [
        "is WGU respected",
        "WGU degree value",
        "WGU hiring",
        "employers accept WGU"
      ],
      "category": "career",
      "tags": [
        "Career",
        "Employment",
        "Employer Perception"
      ],
      "priority": 2,
      "status": "published",
      "internalLinks": [
        "wgu-jobs-after-graduation",
        "wgu-vs-traditional-college"
      ],
      "estimatedReadTime": 9,
      "notes": "Research-based article on employer attitudes",
      "publishedDate": "2025-12-18"
    },
    {
      "id": "054",
      "type": "landing",
      "slug": "wgu-accounting-help",
      "title": "WGU Accounting Help: Expert Support for Your Accounting Degree",
      "primaryKeyword": "WGU accounting help",
      "secondaryKeywords": [
        "WGU accounting tutoring",
        "accounting coursework help",
        "WGU CPA help"
      ],
      "category": "degree-guides",
      "tags": [
        "Accounting",
        "Services",
        "Help"
      ],
      "priority": 2,
      "status": "pending",
      "internalLinks": [
        "wgu-accounting-degree-guide"
      ],
      "estimatedReadTime": 5,
      "notes": "Service-focused landing page for accounting students"
    },
    {
      "id": "055",
      "type": "landing",
      "slug": "wgu-cybersecurity-help",
      "title": "WGU Cybersecurity Help: Pass Your InfoSec Courses and Certs",
      "primaryKeyword": "WGU cybersecurity help",
      "secondaryKeywords": [
        "WGU security help",
        "cybersecurity coursework help",
        "WGU infosec tutoring"
      ],
      "category": "degree-guides",
      "tags": [
        "Cybersecurity",
        "Services",
        "Help"
      ],
      "priority": 2,
      "status": "pending",
      "internalLinks": [
        "wgu-cybersecurity-degree-guide",
        "wgu-certification-guide"
      ],
      "estimatedReadTime": 5,
      "notes": "Service-focused landing page for cybersecurity students"
    },
    {
      "id": "056",
      "type": "blog",
      "slug": "wgu-night-owl-study-schedule",
      "title": "WGU Night Owl Study Schedule: How to Study After Work",
      "primaryKeyword": "WGU study schedule",
      "secondaryKeywords": [
        "WGU night study",
        "study after work",
        "WGU evening routine"
      ],
      "category": "study-tips",
      "tags": [
        "Study Schedule",
        "Time Management",
        "Night Owl"
      ],
      "priority": 3,
      "status": "published",
      "internalLinks": [
        "wgu-study-tips-working-adults",
        "wgu-acceleration-guide"
      ],
      "estimatedReadTime": 7,
      "notes": "Evening and night study strategies for working adults",
      "publishedDate": "2025-12-18"
    },
    {
      "id": "057",
      "type": "blog",
      "slug": "wgu-weekend-warrior-guide",
      "title": "WGU Weekend Warrior: Complete a Course Every Weekend",
      "primaryKeyword": "WGU weekend study",
      "secondaryKeywords": [
        "WGU weekend course",
        "study weekends only",
        "WGU weekend warrior"
      ],
      "category": "study-tips",
      "tags": [
        "Study Schedule",
        "Weekend",
        "Acceleration"
      ],
      "priority": 3,
      "status": "published",
      "publishedDate": "2025-12-19",
      "internalLinks": [
        "wgu-acceleration-guide",
        "wgu-one-term-graduation-guide"
      ],
      "estimatedReadTime": 8,
      "notes": "Weekend-intensive study strategies"
    },
    {
      "id": "058",
      "type": "blog",
      "slug": "wgu-study-resources-guide",
      "title": "Best Free Study Resources for WGU Students in 2025",
      "primaryKeyword": "WGU study resources",
      "secondaryKeywords": [
        "free WGU resources",
        "WGU study materials",
        "WGU learning resources"
      ],
      "category": "study-tips",
      "tags": [
        "Resources",
        "Free",
        "Study Materials"
      ],
      "priority": 2,
      "status": "published",
      "publishedDate": "2025-12-17",
      "internalLinks": [
        "wgu-oa-exam-tips",
        "wgu-study-tips-working-adults"
      ],
      "estimatedReadTime": 10,
      "notes": "Curated list of YouTube, Quizlet, Reddit, etc."
    },
    {
      "id": "059",
      "type": "blog",
      "slug": "wgu-course-order-strategy",
      "title": "WGU Course Order Strategy: Which Classes to Take First",
      "primaryKeyword": "WGU course order",
      "secondaryKeywords": [
        "WGU course sequence",
        "which WGU courses first",
        "WGU class order"
      ],
      "category": "study-tips",
      "tags": [
        "Course Planning",
        "Strategy",
        "Acceleration"
      ],
      "priority": 2,
      "status": "published",
      "publishedDate": "2025-12-17",
      "internalLinks": [
        "wgu-acceleration-guide",
        "wgu-mentor-tips"
      ],
      "estimatedReadTime": 9,
      "notes": "Strategic course sequencing for different goals"
    },
    {
      "id": "060",
      "type": "blog",
      "slug": "wgu-burnout-prevention",
      "title": "Avoiding WGU Burnout: Sustainable Strategies for Long-Term Success",
      "primaryKeyword": "WGU burnout",
      "secondaryKeywords": [
        "WGU stress",
        "avoid burnout WGU",
        "WGU mental health",
        "sustainable WGU pace"
      ],
      "category": "study-tips",
      "tags": [
        "Mental Health",
        "Burnout",
        "Balance"
      ],
      "priority": 2,
      "status": "published",
      "internalLinks": [
        "wgu-study-tips-working-adults",
        "wgu-mentor-tips"
      ],
      "estimatedReadTime": 8,
      "notes": "Self-care, pacing, recognizing warning signs",
      "publishedDate": "2025-12-18"
    }
  ]
}
